xliee_sentry_telegram/__init__.py
xliee_sentry_telegram/plugin.py
xliee_sentry_telegram-0.6.6.dist-info/LICENSE
xliee_sentry_telegram-0.6.6.dist-info/METADATA
xliee_sentry_telegram-0.6.6.dist-info/WHEEL
xliee_sentry_telegram-0.6.6.dist-info/entry_points.txt
xliee_sentry_telegram-0.6.6.dist-info/top_level.txt
xliee_sentry_telegram-0.6.6.dist-info/RECORD
